CHANGES
COPYING
README
common.h
errors.h
ez_setup.py
helpers.h
iBase.c
iBase_Python.h
iBase_array.inl
iBase_handleTempl.def
iGeom.c
iGeom_Python.h
iGeom_doc.h
iGeom_entSet.inl
iGeom_iter.inl
iGeom_tag.inl
iMesh.c
iMeshExtensions.c
iMesh_Python.h
iMesh_doc.h
iMesh_entSet.inl
iMesh_iter.inl
iMesh_tag.inl
iRel.c
iRel_Python.h
iRel_doc.h
iRel_pair.inl
iRel_pairSide.inl
numpy_extensions.h
parse_makefile.py
setup.cfg.example
setup.py
PyTAPS.egg-info/PKG-INFO
PyTAPS.egg-info/SOURCES.txt
PyTAPS.egg-info/dependency_links.txt
PyTAPS.egg-info/not-zip-safe
PyTAPS.egg-info/requires.txt
PyTAPS.egg-info/top_level.txt
doc/Makefile
doc/conf.py
doc/helpers.rst
doc/ibase.rst
doc/igeom.rst
doc/imesh.rst
doc/index.rst
doc/install.rst
doc/irel.rst
doc/c-api/ibase.rst
doc/c-api/igeom.rst
doc/c-api/imesh.rst
doc/c-api/index.rst
doc/tutorial/example.rst
doc/tutorial/from-c.rst
doc/tutorial/igeom.rst
doc/tutorial/imesh.rst
doc/tutorial/index.rst
doc/tutorial/irel.rst
doc/tutorial/sets-tags.rst
doc/tutorial/why-use.rst
perf/perf.c
perf/perf.py
pkg/__init__.py
pkg/helpers.py
test/__init__.py
test/testhelper.py
test/helpers/__init__.py
test/helpers/indexedlist.py
test/helpers/offsetlist.py
test/ibase/__init__.py
test/ibase/ents.py
test/ibase/sets.py
test/ibase/tags.py
test/igeom/__init__.py
test/igeom/adj.py
test/igeom/basic.py
test/igeom/coords.py
test/igeom/creation.py
test/igeom/diff.py
test/igeom/entset.py
test/igeom/iter.py
test/igeom/tags.py
test/imesh/__init__.py
test/imesh/adj.py
test/imesh/basic.py
test/imesh/creation.py
test/imesh/entset.py
test/imesh/iter.py
test/imesh/save.py
test/imesh/tags.py
test/imeshextensions/__init__.py
test/imeshextensions/extensions.py
test/irel/__init__.py
test/irel/basic.py
test/irel/relation.py
tools/tagviewer
tools/volume.py