Metadata-Version: 1.1
Name: PyTAPS
Version: 1.4
Summary: Python bindings for ITAPS interfaces
Home-page: http://packages.python.org/PyTAPS/
Author: Jim Porter
Author-email: jvporter@wisc.edu
License: UNKNOWN
Platform: UNKNOWN
Classifier: Development Status :: 5 - Production/Stable
Classifier: Environment :: Console
Classifier: Intended Audience :: Developers
Classifier: Intended Audience :: Science/Research
Classifier: License :: OSI Approved :: GNU Library or Lesser General Public License (LGPL)
Classifier: Topic :: Scientific/Engineering
Requires: numpy(>=1.3.0)
Provides: itaps
